AUTHORS
LICENSE
README.md
pyproject.toml
setup.py
kpkc/__init__.py
kpkc/kpkc.cpp
kpkc/kpkc.pxd
kpkc/kpkc.pyx
kpkc/test.py
kpkc.egg-info/PKG-INFO
kpkc.egg-info/SOURCES.txt
kpkc.egg-info/dependency_links.txt
kpkc.egg-info/not-zip-safe
kpkc.egg-info/requires.txt
kpkc.egg-info/top_level.txt
kpkc/cppkpkc/kpkc.cpp
kpkc/cppkpkc/kpkc.h