Metadata-Version: 2.1
Name: kpkc
Version: 0.1.0
Summary: A python interface to KPartiteKClique
Home-page: https://github.com/kliem/PyKPartiteKClique
Author: Jonathan Kliem
Author-email: jonathan.kliem@gmail.com
License: GPLv3
Platform: UNKNOWN
Classifier: Development Status :: 2 - Pre-Alpha
Classifier: Intended Audience :: Science/Research
Classifier: License :: OSI Approved :: GNU General Public License v3 (GPLv3)
Classifier: Programming Language :: Python :: 3
Classifier: Topic :: Scientific/Engineering :: Mathematics
Requires-Python: >=3.6
License-File: LICENSE
License-File: AUTHORS
